CHANGES.TXT
LICENSE.TXT
MANIFEST.in
README.rst
USAGE.TXT
setup.py
doc/Makefile
doc/cheatsheet.rst
doc/conf.py
doc/contents.rst
doc/contributing.rst
doc/design.rst
doc/faq.rst
doc/gallery.rst
doc/global.inc
doc/glossary.rst
doc/history.rst
doc/implementation_notes.rst
doc/installation.rst
doc/make.bat
doc/manual_follows1.png
doc/pipeline_functions.rst
doc/propset
doc/proxy_logger.rst
doc/regenerate_figures
doc/release.rst
doc/task.rst
doc/todo.rst
doc/why_ruffus.rst
doc/_templates/index.html
doc/_templates/layout.html
doc/complex_dags/dot/all.dot
doc/complex_dags/dot/non_dag.dot
doc/complex_dags/dot/task17.dot
doc/complex_dags/dot/task17_from_task9.dot
doc/complex_dags/dot/task25_from_task9.dot
doc/complex_dags/jpg/all.jpg
doc/complex_dags/jpg/all_sm.jpg
doc/complex_dags/jpg/non_dag.jpg
doc/complex_dags/jpg/non_dag_sm.jpg
doc/complex_dags/jpg/task17.jpg
doc/complex_dags/jpg/task17_from_task9.jpg
doc/complex_dags/jpg/task17_from_task9_sm.jpg
doc/complex_dags/jpg/task17_sm.jpg
doc/complex_dags/jpg/task25_from_task9.jpg
doc/complex_dags/jpg/task25_from_task9_sm.jpg
doc/complex_dags/png/all.png
doc/complex_dags/png/non_dag.png
doc/complex_dags/png/task17.png
doc/complex_dags/png/task17_from_task9.png
doc/complex_dags/png/task25_from_task9.png
doc/complex_dags/svg/all.svg
doc/complex_dags/svg/non_dag.svg
doc/complex_dags/svg/task17.svg
doc/complex_dags/svg/task17_from_task9.svg
doc/complex_dags/svg/task25_from_task9.svg
doc/decorators/active_if.rst
doc/decorators/check_if_uptodate.rst
doc/decorators/collate.rst
doc/decorators/combinations.rst
doc/decorators/combinations_with_replacement.rst
doc/decorators/decorators.rst
doc/decorators/files.rst
doc/decorators/files_ex.rst
doc/decorators/files_re.rst
doc/decorators/follows.rst
doc/decorators/graphviz.rst
doc/decorators/indicator_objects.rst
doc/decorators/jobs_limit.rst
doc/decorators/merge.rst
doc/decorators/mkdir.rst
doc/decorators/originate.rst
doc/decorators/parallel.rst
doc/decorators/permutations.rst
ruffus.egg-info/PKG-INFO
ruffus.egg-info/SOURCES.txt
ruffus.egg-info/dependency_links.txt
ruffus.egg-info/top_level.txt
