Metadata-Version: 1.2
Name: ruffus
Version: 2.8.4
Summary: Light-weight Python Computational Pipeline Management
Home-page: http://www.ruffus.org.uk
Author: Leo Goodstadt
Author-email: ruffus@llew.org.uk
Maintainer: Leo Goodstadt
Maintainer-email: ruffus_lib@llew.org.uk
License: MIT
Download-URL: https://github.com/cgat-developers/ruffus
Keywords: make task pipeline parallel bioinformatics science
Platform: UNKNOWN
Classifier: Intended Audience :: End Users/Desktop
Classifier: Development Status :: 5 - Production/Stable
Classifier: Intended Audience :: Developers
Classifier: Intended Audience :: Science/Research
Classifier: Intended Audience :: Information Technology
Classifier: License :: OSI Approved :: MIT License
Classifier: Programming Language :: Python
Classifier: Topic :: Scientific/Engineering
Classifier: Topic :: Scientific/Engineering :: Bio-Informatics
Classifier: Topic :: System :: Distributed Computing
Classifier: Topic :: Software Development :: Build Tools
Classifier: Topic :: Software Development :: Build Tools
Classifier: Topic :: Software Development :: Libraries
Classifier: Environment :: Console
